nishant_tts/__init__.py
nishant_tts/client.py
nishant_tts-1.0.0.dist-info/METADATA
nishant_tts-1.0.0.dist-info/WHEEL
nishant_tts-1.0.0.dist-info/top_level.txt
nishant_tts-1.0.0.dist-info/RECORD
