Metadata-Version: 2.4
Name: nishant_tts
Version: 1.0.0
Summary: Client library for cached F5-TTS inference on Modal
Author: Nishant
Requires-Dist: modal
Requires-Dist: numpy
Dynamic: author
Dynamic: requires-dist
Dynamic: summary
